tistory/__init__.py
tistory/get.py
tistory/main.py
tistory/post.py
tistory/oauth2/__init__.py
tistory/oauth2/client.py
tistory/oauth2/main.py
tistory/oauth2/server.py
tistory/oauth2/token.py
tistory_cli-0.1.4.dist-info/METADATA
tistory_cli-0.1.4.dist-info/RECORD
tistory_cli-0.1.4.dist-info/WHEEL
tistory_cli-0.1.4.dist-info/entry_points.txt
tistory_cli-0.1.4.dist-info/top_level.txt
