Metadata-Version: 2.1
Name: tistory-cli
Version: 0.1.4
Summary: The simplest command line tool for Tistory, the Korean blogging platform
Home-page: https://github.com/dgkim5360/tistory-cli-python
Author: Don Kim
Author-email: dgkimdev@gmail.com
License: UNKNOWN
Keywords: Command Line Tool,Tistory,Markdown,blogging
Platform: UNKNOWN
Requires-Dist: secretstorage (>=3.0.0)
Requires-Dist: mistune (>=0.8.3)
